MANIFEST.in
setup.py
ajax_model_listing/__init__.py
ajax_model_listing/classes.py
ajax_model_listing/settings.py
ajax_model_listing/locale/pt_BR/LC_MESSAGES/django.mo
ajax_model_listing/locale/pt_BR/LC_MESSAGES/django.po
ajax_model_listing/static/ajax_model_listing/ajax_model_listing.css
ajax_model_listing/static/ajax_model_listing/ajax_model_listing.js
ajax_model_listing/static/ajax_model_listing/sort_icons/sort_asc.png
ajax_model_listing/static/ajax_model_listing/sort_icons/sort_both.png
ajax_model_listing/static/ajax_model_listing/sort_icons/sort_desc.png
ajax_model_listing/templates/ajax_model_listing/list.html
ajax_model_listing/templates/ajax_model_listing/list_body.html
ajax_model_listing/templates/ajax_model_listing/list_foot.html
ajax_model_listing/templates/ajax_model_listing/list_head.html
django_ajax_model_listing.egg-info/PKG-INFO
django_ajax_model_listing.egg-info/SOURCES.txt
django_ajax_model_listing.egg-info/dependency_links.txt
django_ajax_model_listing.egg-info/top_level.txt