Metadata-Version: 1.0
Name: django-ajax-model-listing
Version: 0.1.5
Summary: Ajax-based model listing for Django. Supports pagination, sorting and filtering. Needs jQuery. Docs coming soon. Demo project here: https://bitbucket.org/victorsilv4/django_ajax_model_listing_demos
Home-page: http://pypi.python.org/pypi/django-ajax-model-listing/
Author: Victor Oliveira da Silva
Author-email: victor_o_silva@hotmail.com
License: Creative Commons Attribution-Noncommercial-Share Alike license
Platform: UNKNOWN
